{
  "layer": {
    "id": "sun_exposure",
    "type": "fill-extrusion",
    "source": "sun_exposure",
    "paint": {
      "fill-extrusion-height": 0.2,
      "fill-extrusion-base": 0.25,
      "fill-extrusion-opacity": 0.8,
      "fill-extrusion-color": [
        "match",

         ["*", ["get", "value"], 10],
        0,
        "#313695",
        1,
        "#4575b4",
        2,
        "#74add1",
        3,
        "#abd9e9",
        4,
        "#e0f3f8",
        5,
        "#ffffbf",
        6,
        "#fee090",
        7,
        "#fdae61",
        8,
        "#f46d43",
        9,
        "#d73027",
        10,
        "#a50026",
        "black"
      ]
    }
  },
  "mapSource": {
    "id": "sun_exposure",
    "type": "geojson",
    "data": {
      "from": "cityPyO",
      "id": "sun_exposure"
    }
  }
}
